ryser/__init__.py
ryser-0.2.0.dist-info/LICENSE
ryser-0.2.0.dist-info/METADATA
ryser-0.2.0.dist-info/WHEEL
ryser-0.2.0.dist-info/RECORD
